uniclip/__init__.py
uniclip/client.py
uniclip/installer.py
uniclip/main.py
uniclip/server.py
uniclip-0.2.0.dist-info/METADATA
uniclip-0.2.0.dist-info/WHEEL
uniclip-0.2.0.dist-info/entry_points.txt
uniclip-0.2.0.dist-info/top_level.txt
uniclip-0.2.0.dist-info/RECORD
