Metadata-Version: 2.1
Name: uniclip
Version: 0.2.0
Summary: A clipboard synchronization tool
Home-page: https://github.com/renxida/uniclip
Author: Cedar Ren
Author-email: cedar.ren@gmail.com
Classifier: Development Status :: 3 - Alpha
Classifier: Intended Audience :: Developers
Classifier: License :: OSI Approved :: MIT License
Classifier: Operating System :: POSIX :: Linux
Classifier: Programming Language :: Python :: 3
Classifier: Programming Language :: Python :: 3.7
Classifier: Programming Language :: Python :: 3.8
Classifier: Programming Language :: Python :: 3.9
Requires-Python: >=3.7
Requires-Dist: fastapi
Requires-Dist: uvicorn
Requires-Dist: waitress
Requires-Dist: pydantic
Requires-Dist: requests
Requires-Dist: pyperclip
Requires-Dist: pyyaml
